{
  "DOGEUSDT": [
    {
      "symbol": "DOGEUSDT",
      "size": "945",
      "orderId": "1318662889371459623",
      "clientOid": "1318661548009107456",
      "baseVolume": "945",
      "fee": "-0.0970704",
      "price": "",
      "priceAvg": "0.1712",
      "status": "filled",
      "side": "buy",
      "force": "gtc",
      "totalProfits": "0",
      "posSide": "net",
      "marginCoin": "USDT",
      "quoteVolume": "161.784",
      "leverage": "20",
      "marginMode": "crossed",
      "enterPointSource": "api",
      "tradeSide": "buy_single",
      "posMode": "one_way_mode",
      "orderType": "market",
      "orderSource": "plan_market",
      "presetStopSurplusPrice": "",
      "presetStopLossPrice": "",
      "posAvg": "0.1712",
      "reduceOnly": "YES",
      "cTime": "1750119653077",
      "uTime": "1750119653139"
    },
    {
      "symbol": "DOGEUSDT",
      "size": "193",
      "orderId": "1317226893694066703",
      "clientOid": "1317226893698260997",
      "baseVolume": "193",
      "fee": "-0.00651297",
      "price": "0.16873",
      "priceAvg": "0.16873",
      "status": "filled",
      "side": "buy",
      "force": "gtc",
      "totalProfits": "0.47671",
      "posSide": "net",
      "marginCoin": "USDT",
      "quoteVolume": "32.5648",
      "leverage": "20",
      "marginMode": "crossed",
      "enterPointSource": "api",
      "tradeSide": "buy_single",
      "posMode": "one_way_mode",
      "orderType": "limit",
      "orderSource": "normal",
      "presetStopSurplusPrice": "",
      "presetStopLossPrice": "",
      "posAvg": "0.1712",
      "reduceOnly": "YES",
      "cTime": "1749777285026",
      "uTime": "1750119322638"
    },
    {
      "symbol": "DOGEUSDT",
      "size": "1138",
      "orderId": "1317226528621846530",
      "clientOid": "1317226528638623777",
      "baseVolume": "1138",
      "fee": "-0.03896512",
      "price": "0.1712",
      "priceAvg": "0.1712",
      "status": "filled",
      "side": "sell",
      "force": "gtc",
      "totalProfits": "0",
      "posSide": "net",
      "marginCoin": "USDT",
      "quoteVolume": "194.8256",
      "leverage": "20",
      "marginMode": "crossed",
      "enterPointSource": "api",
      "tradeSide": "sell_single",
      "posMode": "one_way_mode",
      "orderType": "limit",
      "orderSource": "normal",
      "presetStopSurplusPrice": "",
      "presetStopLossPrice": "",
      "posAvg": "",
      "reduceOnly": "NO",
      "cTime": "1749777197989",
      "uTime": "1749777279996"
    }
  ]
}